<?xml version="1.0" encoding="utf-8" ?>
<odoo noupdate="1">
    <record id="stock_location_highbay_demo" model="stock.location">
        <field name="name">Highbay</field>
        <field name="location_id" ref="stock.stock_location_stock" />
    </record>
    <record id="stock_location_highbay_a_demo" model="stock.location">
        <field name="name">Bay A</field>
        <field name="location_id" ref="stock_location_highbay_demo" />
    </record>
    <record id="stock_location_highbay_a_1_demo" model="stock.location">
        <field name="name">Bin 1</field>
        <field name="location_id" ref="stock_location_highbay_a_demo" />
    </record>
    <record id="stock_location_highbay_demo_1_2" model="stock.location">
        <field name="name">Bin 2</field>
        <field name="location_id" ref="stock_location_highbay_a_demo" />
    </record>
    <record id="stock_location_handover_demo" model="stock.location">
        <field name="name">Handover</field>
        <field name="location_id" ref="stock.stock_location_stock" />
    </record>
</odoo>
